pytelegraf_exec.py
pytelegraf_exec-0.1.2.dist-info/DESCRIPTION.rst
pytelegraf_exec-0.1.2.dist-info/METADATA
pytelegraf_exec-0.1.2.dist-info/RECORD
pytelegraf_exec-0.1.2.dist-info/WHEEL
pytelegraf_exec-0.1.2.dist-info/metadata.json
pytelegraf_exec-0.1.2.dist-info/top_level.txt
