Metadata-Version: 2.0
Name: pytelegraf-exec
Version: 0.1.2
Summary: A easy to use line format convertor for influxdb.
Home-page: UNKNOWN
Author: Randy Coburn
Author-email: development@newvoicemedia.com
License: MIT
Keywords: telegraf influxdb monitoring
Platform: UNKNOWN
Classifier: Development Status :: 4 - Beta
Classifier: Intended Audience :: Developers
Classifier: Topic :: System :: Monitoring
Classifier: License :: OSI Approved :: MIT License
Classifier: Programming Language :: Python :: 2.7
Classifier: Programming Language :: Python :: 3
Classifier: Programming Language :: Python :: 3.3
Classifier: Programming Language :: Python :: 3.4
Classifier: Programming Language :: Python :: 3.5
